rapid_pdf-0.1.4.dist-info/METADATA
rapid_pdf-0.1.4.dist-info/WHEEL
rapid_pdf/__init__.py
rapid_pdf/rapid_pdf.abi3.so
rapid_pdf-0.1.4.dist-info/RECORD
