Metadata-Version: 2.4
Name: rapid_pdf
Version: 0.1.4
Classifier: Programming Language :: Rust
Classifier: Programming Language :: Python :: Implementation :: CPython
Classifier: Programming Language :: Python :: 3
Summary: A fast PDF text extractor written in Rust. Aim for speed and low memory usage. And improve performance with Large Language Models when handling massive amount of Document.
Requires-Python: >=3.7
